Lab2-Lalaguna.v
module deMorgan(
    input a,b,
    output NAND1,negativeOR1,NOR1,negativeAND1
);
    wire notA,notB;

    not(notA,a);
    not(notB,b);

    nand(NAND1,a,b);             // ~((a)(b))
    or(negativeOR1,notA,notB);   // (~a)+(~b)

    nor(NOR1,a,b);               // ~(a+b)
    and(negativeAND1,notA,notB); // (~a)(~b)
endmodule

module oneB( //AND Gate
    input a,b,
    output x
);
    wire notA,notB,notAOrnotB;

    not(notA,a);
    not(notB,b);
    or(notAOrnotB,notA,notB);
    not(x,notAOrnotB);
endmodule

module twoA( //AND Gate
    input a,b,
    output x
);
    wire nor1,nor2;

    nor(nor1,a,a);
    nor(nor2,b,b);
    nor(x,nor1,nor2);
endmodule

module twoB( //OR Gate
    input a,b,
    output x
);
    wire nand1,nand2;

    nand(nand1,a,a);
    nand(nand2,b,b);
    nand(x,nand1,nand2);
endmodule

module Experiment2;
    reg a,b;
    wire
        NAND1,negativeOR1,NOR1,negativeAND1,
        oneBresult,
        twoAresult,
        twoBresult
        ;
    deMorgan A1(a,b,NAND1,negativeOR1,NOR1,negativeAND1);
    oneB B1(a,b,oneBresult);
    twoA A2(a,b,twoAresult);
    twoB B2(a,b,twoBresult);

    initial
        begin
            $dumpfile("Lab2-Lalaguna.vcd");
	        $dumpvars(-1, A1,B1,A2,B2);
	        $monitor("%b",  NAND1,negativeOR1,NOR1,negativeAND1,
                            oneBresult,
                            twoAresult,
                            twoBresult);
        end
    initial begin
        #1 $display("DeMorgan's Law");
        #1 $display("~((a)(b))");
        #1 a=0; b=0;
           $monitor("a=%b, b=%b, n=%b",a,b,NAND1);
        #1 a=0; b=1;
        #1 a=1; b=0;
        #1 a=1; b=1;

       
        #1 $display("(~a)+(~b)");
        #1 a=0; b=0;
           $monitor("a=%b, b=%b, n=%b",a,b,negativeOR1);
        #1 a=0; b=1;
        #1 a=1; b=0;
        #1 a=1; b=1;
        #1 if (NAND1==negativeOR1) begin
            $display("Therefore, ~((a)(b)) == (~a)+(~b)\n");
        end else begin
            $display("Therefore, ~((a)(b)) != (~a)+(~b)\n");
        end

        #1 $display("~(a+b)");
        #1 a=0; b=0;
           $monitor("a=%b, b=%b, n=%b",a,b,NOR1);
        #1 a=0; b=1;
        #1 a=1; b=0;
        #1 a=1; b=1;

        #1 $display("(~a)(~b)");
        #1 a=0; b=0;
           $monitor("a=%b, b=%b, n=%b",a,b,negativeAND1);
        #1 a=0; b=1;
        #1 a=1; b=0;
        #1 a=1; b=1;
        #1 if (NOR1==negativeAND1) begin
            $display("Therefore, ~(a+b) == (~a)(~b)\n");
        end else begin
            $display("Therefore, ~(a+b) != (~a)(~b)\n");
        end

        #1 $display("part 1B");
           $monitor("a=%b, b=%b, n=%b",a,b,oneBresult);
        #1 a=0; b=1;
        #1 a=1; b=0;
        #1 a=1; b=1;
        #1 $display("\npart 2A");
           $monitor("a=%b, b=%b, n=%b",a,b,twoAresult);
        #1 a=1; b=0;
        #1 a=0; b=1;
        #1 a=0; b=0;
        #1 $display("\npart 2B");
           $monitor("a=%b, b=%b, n=%b",a,b,twoBresult);
        #1 a=0; b=1;
        #1 a=1; b=0;
        #1 a=1; b=1;
        #1 $finish;
    end
endmodule

Lab2-Lalaguna.vcd
$date
	Wed Dec 14 11:41:19 2022
$end
$version
	Icarus Verilog
$end
$timescale
	1s
$end
$scope module Experiment2 $end
$scope module A1 $end
$var wire 1 ! NAND1 $end
$var wire 1 " NOR1 $end
$var wire 1 # a $end
$var wire 1 $ b $end
$var wire 1 % negativeAND1 $end
$var wire 1 & negativeOR1 $end
$var wire 1 ' notA $end
$var wire 1 ( notB $end
$upscope $end
$upscope $end
$scope module Experiment2 $end
$scope module B1 $end
$var wire 1 # a $end
$var wire 1 $ b $end
$var wire 1 ) notA $end
$var wire 1 * notAOrnotB $end
$var wire 1 + notB $end
$var wire 1 , x $end
$upscope $end
$upscope $end
$scope module Experiment2 $end
$scope module A2 $end
$var wire 1 # a $end
$var wire 1 $ b $end
$var wire 1 - nor1 $end
$var wire 1 . nor2 $end
$var wire 1 / x $end
$upscope $end
$upscope $end
$scope module Experiment2 $end
$scope module B2 $end
$var wire 1 # a $end
$var wire 1 $ b $end
$var wire 1 0 nand1 $end
$var wire 1 1 nand2 $end
$var wire 1 2 x $end
$upscope $end
$upscope $end
$enddefinitions $end
$comment Show the parameter values. $end
$dumpall
$end
#0
$dumpvars
x2
x1
x0
x/
x.
x-
x,
x+
x*
x)
x(
x'
x&
x%
x$
x#
x"
x!
$end
#3
0,
1&
1%
0/
1*
02
1(
1.
1+
11
1'
1!
1"
1-
1)
10
0$
0#
#4
0%
12
0(
0"
0.
0+
01
1$
#5
1(
1.
1+
11
0'
0-
0)
00
0$
1#
#6
1,
0&
1/
0*
0(
0!
0.
0+
01
1$
#8
0,
1&
1%
0/
1*
02
1(
1.
1+
11
1'
1!
1"
1-
1)
10
0$
0#
#9
0%
12
0(
0"
0.
0+
01
1$
#10
1(
1.
1+
11
0'
0-
0)
00
0$
1#
#11
1,
0&
1/
0*
0(
0!
0.
0+
01
1$
#14
0,
1&
1%
0/
1*
02
1(
1.
1+
11
1'
1!
1"
1-
1)
10
0$
0#
#15
0%
12
0(
0"
0.
0+
01
1$
#16
1(
1.
1+
11
0'
0-
0)
00
0$
1#
#17
1,
0&
1/
0*
0(
0!
0.
0+
01
1$
#19
0,
1&
1%
0/
1*
02
1(
1.
1+
11
1'
1!
1"
1-
1)
10
0$
0#
#20
0%
12
0(
0"
0.
0+
01
1$
#21
1(
1.
1+
11
0'
0-
0)
00
0$
1#
#22
1,
0&
1/
0*
0(
0!
0.
0+
01
1$
#25
0,
1&
0/
1*
1'
1!
1-
1)
10
0#
#26
1(
1.
1+
11
0'
0-
0)
00
0$
1#
#27
1,
0&
1/
0*
0(
0!
0.
0+
01
1$
#29
0,
1&
0/
1*
1(
1!
1.
1+
11
0$
#30
0(
0.
0+
01
1'
1-
1)
10
1$
0#
#31
1%
02
1(
1"
1.
1+
11
0$
#33
0%
12
0(
0"
0.
0+
01
1$
#34
1(
1.
1+
11
0'
0-
0)
00
0$
1#
#35
1,
0&
1/
0*
0(
0!
0.
0+
01
1$
