Lab3-Lalaguna.v
module part1minterm(
    input a,b,c,
    output i
);
    // reference: !A!B + !BC + B!C
    wire notA,notB,notC,BnotC,notBC,notAnotB;

    not(notA,a);
    not(notB,b);
    not(notC,c);

    and(BnotC,b,notC);
    and(notBC,notB,c);
    and(notAnotB,notA,notB);

    or(i,notAnotB,notBC,BnotC);
endmodule

module part1Maxterm(
    input a,b,c,
    output i
);
    // reference: (!A+B+C)(!B+!C)
    wire notA,notB,notC,notABC,notBnotC;

    not(notA,a);
    not(notB,b);
    not(notC,c);

    or(notABC,notA,b,c);
    or(notBnotC,notB,notC);

    and(i,notABC,notBnotC);
endmodule

module part5Minterm(
    input a,b,c,d,
    output i
);
    // reference: !A!C!B+!ADB+!AD!C+A!BCD+AB!C
    wire notA,notB,notC,
        notAnotCnotB,notADB,
        notADnotC,notABCD,ABnotC;

    not(notA,a);
    not(notB,b);
    not(notC,c);

    and(notAnotCnotB,notA,notC,notB);
    and(notADB,notA,d,b);
    and(notADnotC,notA,d,notC);
    and(AnotBCD,a,notB,c,d);
    and(ABnotC,a,b,notC);

    or(i,notAnotCnotB,notADB,notADnotC,AnotBCD,ABnotC);
endmodule

module part5Maxterm(
    input a,b,c,d,
    output i
);
    // reference: (!A+!B+!C)(!A+B+C)(A+!B+D)(A+B+!C)(!C+D)
    wire notA,notB,notC,
        notAnotBnotC,notABC,AnotBD,
        ABnotC,notCD;

    not(notA,a);
    not(notB,b);
    not(notC,c);

    or(notAnotBnotC,notA,notB,notC);
    or(notABC,notA,b,c);
    or(AnotBD,a,notB,d);
    or(ABnotC,a,b,notC);
    or(notCD,notC,d);

    and(i,notAnotBnotC,notABC,AnotBD,ABnotC,notCD);
endmodule

module Lab3TestBench;
    reg a,b,c,d;
    wire oneMinterm,oneMaxterm,fiveMinterm,fiveMaxterm;

    part1minterm P1Min(a,b,c,oneMinterm);
    part1Maxterm P1Max(a,b,c,oneMaxterm);
    part5Minterm P5Min(a,b,c,d,fiveMinterm);
    part5Maxterm P5Max(a,b,c,d,fiveMaxterm);

    initial
        begin
            $dumpfile("Lab3-Lalaguna.vcd");
	        $dumpvars(-1, P1Min,P1Max,P5Min,P5Max);
	        $monitor("%b",  oneMinterm,oneMaxterm,fiveMinterm,fiveMaxterm);
        end
    initial begin
        #1 a=0;b=0;c=0;
        $display("part1 minterm: !A!B + !BC + B!C");
        $monitor("a=%b, b=%b, c=%b : i=%b",a,b,c,oneMinterm);
        #1 a=0;b=0;c=1;
        #1 a=0;b=1;c=0;
        #1 a=0;b=1;c=1;
        #1 a=1;b=0;c=0;
        #1 a=1;b=0;c=1;
        #1 a=1;b=1;c=0;
        #1 a=1;b=1;c=1;

        #1 a=0;b=0;c=0;
        $display("\npart1 maxterm: (!A+B+C)(!B+!C)");
        $monitor("a=%b, b=%b, c=%b : i1=%b",a,b,c,oneMaxterm);
        #1 a=0;b=0;c=1;
        #1 a=0;b=1;c=0;
        #1 a=0;b=1;c=1;
        #1 a=1;b=0;c=0;
        #1 a=1;b=0;c=1;
        #1 a=1;b=1;c=0;
        #1 a=1;b=1;c=1;

        #1 a=0;b=0;c=0;d=0;
        $display("\npart5 minterm: !A!C!B+!ADB+!AD!C+A!BCD+AB!C");
        $monitor("a=%b, b=%b, c=%b, d=%b : i1=%b",a,b,c,d,fiveMinterm);
        #1 a=0;b=0;c=0;d=1;
        #1 a=0;b=0;c=1;d=0;
        #1 a=0;b=0;c=1;d=1;
        #1 a=0;b=1;c=0;d=0;
        #1 a=0;b=1;c=0;d=1;
        #1 a=0;b=1;c=1;d=0;
        #1 a=0;b=1;c=1;d=1;
        #1 a=1;b=0;c=0;d=0;
        #1 a=1;b=0;c=0;d=1;
        #1 a=1;b=0;c=1;d=0;
        #1 a=1;b=0;c=1;d=1;
        #1 a=1;b=1;c=0;d=0;
        #1 a=1;b=1;c=0;d=1;
        #1 a=1;b=1;c=1;d=0;
        #1 a=1;b=1;c=1;d=1;

        #1 a=0;b=0;c=0;d=0;
        $display("\npart5 maxterm: (!A+!B+!C)(!A+B+C)(A+!B+D)(A+B+!C)(!C+D)");
        $monitor("a=%b, b=%b, c=%b, d=%b : i1=%b",a,b,c,d,fiveMaxterm);
        #1 a=0;b=0;c=0;d=1;
        #1 a=0;b=0;c=1;d=0;
        #1 a=0;b=0;c=1;d=1;
        #1 a=0;b=1;c=0;d=0;
        #1 a=0;b=1;c=0;d=1;
        #1 a=0;b=1;c=1;d=0;
        #1 a=0;b=1;c=1;d=1;
        #1 a=1;b=0;c=0;d=0;
        #1 a=1;b=0;c=0;d=1;
        #1 a=1;b=0;c=1;d=0;
        #1 a=1;b=0;c=1;d=1;
        #1 a=1;b=1;c=0;d=0;
        #1 a=1;b=1;c=0;d=1;
        #1 a=1;b=1;c=1;d=0;
        #1 a=1;b=1;c=1;d=1;
    end
endmodule

Lab3-Lalaguna.vcd
$date
	Wed Dec 14 11:42:32 2022
$end
$version
	Icarus Verilog
$end
$timescale
	1s
$end
$scope module Lab3TestBench $end
$scope module P1Min $end
$var wire 1 ! BnotC $end
$var wire 1 " a $end
$var wire 1 # b $end
$var wire 1 $ c $end
$var wire 1 % i $end
$var wire 1 & notA $end
$var wire 1 ' notAnotB $end
$var wire 1 ( notB $end
$var wire 1 ) notBC $end
$var wire 1 * notC $end
$upscope $end
$upscope $end
$scope module Lab3TestBench $end
$scope module P1Max $end
$var wire 1 " a $end
$var wire 1 # b $end
$var wire 1 $ c $end
$var wire 1 + i $end
$var wire 1 , notA $end
$var wire 1 - notABC $end
$var wire 1 . notB $end
$var wire 1 / notBnotC $end
$var wire 1 0 notC $end
$upscope $end
$upscope $end
$scope module Lab3TestBench $end
$scope module P5Min $end
$var wire 1 1 ABnotC $end
$var wire 1 2 AnotBCD $end
$var wire 1 " a $end
$var wire 1 # b $end
$var wire 1 $ c $end
$var wire 1 3 d $end
$var wire 1 4 i $end
$var wire 1 5 notA $end
$var wire 1 6 notADB $end
$var wire 1 7 notADnotC $end
$var wire 1 8 notAnotCnotB $end
$var wire 1 9 notB $end
$var wire 1 : notC $end
$upscope $end
$upscope $end
$scope module Lab3TestBench $end
$scope module P5Max $end
$var wire 1 ; ABnotC $end
$var wire 1 < AnotBD $end
$var wire 1 " a $end
$var wire 1 # b $end
$var wire 1 $ c $end
$var wire 1 3 d $end
$var wire 1 = i $end
$var wire 1 > notA $end
$var wire 1 ? notABC $end
$var wire 1 @ notAnotBnotC $end
$var wire 1 A notB $end
$var wire 1 B notC $end
$var wire 1 C notCD $end
$upscope $end
$upscope $end
$enddefinitions $end
$comment Show the parameter values. $end
$dumpall
$end
#0
$dumpvars
xC
xB
xA
x@
x?
x>
x=
x<
x;
x:
x9
x8
x7
x6
x5
x4
x3
x2
x1
x0
x/
x.
x-
x,
x+
x*
x)
x(
x'
x&
x%
x$
x#
x"
x!
$end
#1
1=
14
1+
1;
1C
1/
1%
1<
1'
1@
18
10
1*
0)
1B
1:
1.
1-
1(
0!
1A
1?
19
06
1,
1&
1>
15
02
01
0$
0#
0"
#2
0=
04
0;
xC
08
07
00
0*
1)
0B
0:
1$
#3
x=
x4
1!
1%
1C
x7
0'
x<
10
1*
0)
1B
1:
0.
0(
0A
1;
09
x6
0$
1#
#4
0+
0%
0/
0!
xC
07
00
0*
0B
0:
1$
#5
04
0=
1C
1/
10
1*
1B
1:
1.
0-
1(
1A
0?
19
06
0,
0&
0>
1<
05
0$
0#
1"
#6
x=
x4
1+
1%
xC
00
1-
0*
1)
0B
1?
0:
x2
1$
#7
1=
14
1!
1%
1C
11
10
1*
0)
1B
1:
02
0.
0(
0A
09
0$
1#
#8
0=
04
0+
0%
0/
0!
0@
xC
01
00
0*
0B
0:
1$
#9
1=
14
1+
1%
1C
1/
1'
1@
18
x7
10
1*
1B
1:
1.
1(
1A
19
1,
1&
1>
1<
1;
15
0$
0#
0"
#10
0=
04
0;
xC
08
07
00
0*
1)
0B
0:
1$
#11
x=
x4
1!
1%
1C
x7
0'
x<
10
1*
0)
1B
1:
0.
0(
0A
1;
09
x6
0$
1#
#12
0+
0%
0/
0!
xC
07
00
0*
0B
0:
1$
#13
04
0=
1C
1/
10
1*
1B
1:
1.
0-
1(
1A
0?
19
06
0,
0&
0>
1<
05
0$
0#
1"
#14
x=
x4
1+
1%
xC
00
1-
0*
1)
0B
1?
0:
x2
1$
#15
1=
14
1!
1%
1C
11
10
1*
0)
1B
1:
02
0.
0(
0A
09
0$
1#
#16
0=
04
0+
0%
0/
0!
0@
xC
01
00
0*
0B
0:
1$
#17
14
1=
1+
1%
1/
1'
1@
18
1C
10
1*
1B
1:
1.
1(
1A
19
1,
1&
1>
1<
1;
15
03
0$
0#
0"
#18
17
13
#19
0=
04
0;
08
0C
07
00
0*
1)
0B
0:
03
1$
#20
1C
13
#21
1!
1%
0'
0<
10
1*
0)
1B
1:
0.
0(
0A
1;
09
03
0$
1#
#22
1=
14
1<
16
17
13
#23
0=
04
0+
0%
0/
0!
0<
0C
06
07
00
0*
0B
0:
03
1$
#24
1=
14
1<
1C
16
13
#25
0=
04
1/
10
1*
1B
1:
1.
0-
1(
1A
0?
19
06
0,
0&
0>
05
03
0$
0#
1"
#26
13
#27
1+
1%
0C
00
1-
0*
1)
0B
1?
0:
03
1$
#28
1=
14
1C
12
13
#29
14
1!
1%
11
10
1*
0)
1B
1:
02
0.
0(
0A
09
03
0$
1#
#30
13
#31
04
0=
0+
0%
0/
0!
0@
01
0C
00
0*
0B
0:
03
1$
#32
1C
13
#33
1=
14
1+
1%
1/
1'
1@
18
10
1*
1B
1:
1.
1(
1A
19
1,
1&
1>
1<
1;
15
03
0$
0#
0"
#34
17
13
#35
0=
04
0;
08
0C
07
00
0*
1)
0B
0:
03
1$
#36
1C
13
#37
1!
1%
0'
0<
10
1*
0)
1B
1:
0.
0(
0A
1;
09
03
0$
1#
#38
1=
14
1<
16
17
13
#39
0=
04
0+
0%
0/
0!
0<
0C
06
07
00
0*
0B
0:
03
1$
#40
1=
14
1<
1C
16
13
#41
0=
04
1/
10
1*
1B
1:
1.
0-
1(
1A
0?
19
06
0,
0&
0>
05
03
0$
0#
1"
#42
13
#43
1+
1%
0C
00
1-
0*
1)
0B
1?
0:
03
1$
#44
1=
14
1C
12
13
#45
14
1!
1%
11
10
1*
0)
1B
1:
02
0.
0(
0A
09
03
0$
1#
#46
13
#47
04
0=
0+
0%
0/
0!
0@
01
0C
00
0*
0B
0:
03
1$
#48
1C
13
