Lab4-Lalaguna.v
module part1(
    input a,b,
    output f
);
    assign f = (~a & b)|(a & ~b);
endmodule

module part3(
    input a,b,c,
    output g
);
    wire notC,AB,AC,BnotC;

    not(notC,c);
    and(AB,a,b);
    and(AC,a,c);
    and(BnotC,b,notC);
    or(g,AC,BnotC,AB);
endmodule

module part5(
    input a,b,c,d,
    output h
);
    wire ABC,CD,notCD,nor1,and2;

    and(ABC,a,b,c);
    or(CD,c,d);
    not(notCD,CD);
    nor(nor1,ABC,notCD);
    and(and2,notCD,ABC);
    or(h,and2,d,nor1);
endmodule

module Lab4TB;
    reg a,b,c,d;
    wire f,g,h;

    part1 p1(a,b,f);
    part3 p3(a,b,c,g);
    part5 p5(a,b,c,d,h);

    initial
        begin
            $dumpfile("Lab4-Lalaguna.vcd");
	        $dumpvars(-1, p1,p3,p5);
	        $monitor("%b",  f,g,h);
        end
    initial begin
        #1 a=0; b=0;
        #1 $display("part1");
           $monitor($time,,,"a=%b, b=%b : f=%b",a,b,f);
        #1 a=0; b=1;
        #1 a=1; b=0;
        #1 a=1; b=1;

        #1 a=0; b=0; c=0;
        #1 $display("part3");
           $monitor($time,,,"a=%b, b=%b, c-%b : g=%b",a,b,c,g);
        #1 a=0; b=0; c=1;
        #1 a=0; b=1; c=0;
        #1 a=0; b=1; c=1;
        #1 a=1; b=0; c=0;
        #1 a=1; b=0; c=1;
        #1 a=1; b=1; c=0;
        #1 a=1; b=1; c=1;

        #1 a=0; b=0; c=0; d=0;
        #1 $display("part5");
           $monitor($time,,,"a=%b, b=%b, c-%b, d=%b : h=%b",a,b,c,d,h);
        #1 a=0; b=0; c=0; d=1;
        #1 a=0; b=0; c=1; d=0;
        #1 a=0; b=0; c=1; d=1;
        #1 a=0; b=1; c=0; d=0;
        #1 a=0; b=1; c=0; d=1;
        #1 a=0; b=1; c=1; d=0;
        #1 a=0; b=1; c=1; d=1;
        #1 a=1; b=0; c=0; d=0;
        #1 a=1; b=0; c=0; d=1;
        #1 a=1; b=0; c=1; d=0;
        #1 a=1; b=0; c=1; d=1;
        #1 a=1; b=1; c=0; d=0;
        #1 a=1; b=1; c=0; d=1;
        #1 a=1; b=1; c=1; d=0;
        #1 a=1; b=1; c=1; d=1;
    end
endmodule

Lab4-Lalaguna.vcd
$date
	Wed Dec 14 11:43:24 2022
$end
$version
	Icarus Verilog
$end
$timescale
	1s
$end
$scope module Lab4TB $end
$scope module p1 $end
$var wire 1 ! a $end
$var wire 1 " b $end
$var wire 1 # f $end
$upscope $end
$upscope $end
$scope module Lab4TB $end
$scope module p3 $end
$var wire 1 $ AB $end
$var wire 1 % AC $end
$var wire 1 & BnotC $end
$var wire 1 ! a $end
$var wire 1 " b $end
$var wire 1 ' c $end
$var wire 1 ( g $end
$var wire 1 ) notC $end
$upscope $end
$upscope $end
$scope module Lab4TB $end
$scope module p5 $end
$var wire 1 * ABC $end
$var wire 1 + CD $end
$var wire 1 ! a $end
$var wire 1 , and2 $end
$var wire 1 " b $end
$var wire 1 ' c $end
$var wire 1 - d $end
$var wire 1 . h $end
$var wire 1 / nor1 $end
$var wire 1 0 notCD $end
$upscope $end
$upscope $end
$enddefinitions $end
$comment Show the parameter values. $end
$dumpall
$end
#0
$dumpvars
x0
x/
x.
x-
x,
x+
x*
x)
x(
x'
x&
x%
x$
x#
x"
x!
$end
#1
0#
0(
0,
0&
0$
0%
0*
0"
0!
#3
1#
x(
x&
1"
#4
0&
x%
0"
1!
#5
0#
1(
x,
1$
x&
x*
1"
#6
0(
0,
1)
0&
0$
0%
0*
0'
0"
0!
#8
1.
1/
00
0)
1+
1'
#9
x.
1(
x/
1&
x0
1#
1)
x+
0'
1"
#10
1.
0(
1/
0&
00
0)
1+
1'
#11
x.
x/
x0
1)
x+
0'
0"
1!
#12
1.
1/
1(
00
0)
1%
1+
1'
#13
x.
x/
0#
1&
x0
1)
0%
x+
1$
0'
1"
#14
0&
0/
00
0)
1%
1*
1+
1'
#15
10
0(
0/
0.
1)
0+
0$
0%
0*
0-
0'
0"
0!
#17
1/
00
1+
1.
1-
#18
0)
0-
1'
#19
1-
#20
0.
1(
0/
1&
10
1#
1)
0+
0-
0'
1"
#21
1/
00
1+
1.
1-
#22
0(
0&
0)
0-
1'
#23
1-
#24
0.
0/
10
1)
0+
0-
0'
0"
1!
#25
1/
00
1+
1.
1-
#26
1(
0)
1%
0-
1'
#27
1-
#28
0.
0/
0#
1&
10
1)
0%
0+
1$
0-
0'
1"
#29
1/
00
1+
1.
1-
#30
0.
0&
0/
0)
1%
1*
0-
1'
#31
1.
1-
