Lab5-Lalaguna.v
module halfAdder(
    input A, B, 
    output Sum, Carry
);
    and(Carry,A,B);
    xor(Sum,A,B);
endmodule

module fullAdder(
    input a,b,c_In, 
    output sum,c_out
);
    wire xor1,and1,and2;

    xor(xor1,a,b);
    xor(sum,xor1,c_In);
    and(and2,a,b);
    and(and1,xor1,c_In);
    or(c_out,and1,and2);
endmodule

module halfSubtract(
    input A,B, 
    output D,bOut
);
    wire not1;

    xor(D,A,B);
    not(not1,A);
    and(bOut,B,not1);
endmodule

module fullSubtract(
    input A,B,bIn,
    output D,bOut
);
    wire not1,xor1,and1,not2,and2;

    not(not1,A);
    xor(xor1,A,B);
    and(and1,not1,B);
    not(not2,xor1);
    xor(D,xor1,bIn);
    and(and2,not2,bIn);
    or(bOut,and2,and1);
endmodule

module Lab5TB;
    reg a,b,c_In,bIn;
    wire sum,carry,
         sum1,c_out,
         D,bOut,
         D1,bOut1
    ;

    halfAdder HFADD(a,b,sum,carry);
    fullAdder FLADD(a,b,c_In,sum1,c_out);
    halfSubtract HFSUB(a,b,D,bOut);
    fullSubtract FFSUB(a,b,bIn,D1,bOut1);

    initial
        begin
            $dumpfile("Lab5-Lalaguna.vcd");
	        $dumpvars(-1, HFADD,FLADD,HFSUB,FFSUB);
	        $monitor("%b",  sum,carry,
                            sum1,c_out,
                            D,bOut,
                            D1,bOut1);
        end
    initial begin
        #1 a=0; b=0;
        #1 $display("Simulating Half Adder");
           $monitor("A=%b, B=%b, sum=%b, carry=%b", a,b,sum,carry);
        #1 a=0; b=1;
        #1 a=1; b=0;
        #1 a=1; b=1;
        
        #1 a=0; b=0; c_In=0;
        #1 $display("Simulating Full Adder");
           $monitor("A=%b, B=%b, c_In=%b, sum=%b, C_out=%b",a,b,c_In,sum1,c_out);
        #1 a=0; b=0; c_In=1;
        #1 a=0; b=1; c_In=0;
        #1 a=0; b=1; c_In=1;
        #1 a=1; b=0; c_In=0;
        #1 a=1; b=0; c_In=1;
        #1 a=1; b=1; c_In=0;
        #1 a=1; b=1; c_In=1;

        #1 a=0; b=0; 
        #1 $display("Simulating Half Subtract");
           $monitor("A=%b, B=%b, D=%b, bOut=%b",a,b,D,bOut);
        #1 a=0; b=1; 
        #1 a=1; b=0; 
        #1 a=1; b=1; 

        #1 a=0; b=0; bIn=0;
        #1 $display("Simulating Full Subtract");
           $monitor("A=%b, B=%b, bIn=%b, D=%b, bOut=%b", a,b,bIn,D1,bOut1);
        #1 a=0; b=0; bIn=1;
        #1 a=0; b=1; bIn=0;
        #1 a=0; b=1; bIn=1;
        #1 a=1; b=0; bIn=0;
        #1 a=1; b=0; bIn=1;
        #1 a=1; b=1; bIn=0;
        #1 a=1; b=1; bIn=1;

        #1 $finish;  
    end
endmodule

Lab5-Lalaguna.vcd
$date
	Wed Dec 14 11:44:09 2022
$end
$version
	Icarus Verilog
$end
$timescale
	1s
$end
$scope module Lab5TB $end
$scope module HFADD $end
$var wire 1 ! A $end
$var wire 1 " B $end
$var wire 1 # Carry $end
$var wire 1 $ Sum $end
$upscope $end
$upscope $end
$scope module Lab5TB $end
$scope module FLADD $end
$var wire 1 ! a $end
$var wire 1 % and1 $end
$var wire 1 & and2 $end
$var wire 1 " b $end
$var wire 1 ' c_In $end
$var wire 1 ( c_out $end
$var wire 1 ) sum $end
$var wire 1 * xor1 $end
$upscope $end
$upscope $end
$scope module Lab5TB $end
$scope module HFSUB $end
$var wire 1 ! A $end
$var wire 1 " B $end
$var wire 1 + D $end
$var wire 1 , bOut $end
$var wire 1 - not1 $end
$upscope $end
$upscope $end
$scope module Lab5TB $end
$scope module FFSUB $end
$var wire 1 ! A $end
$var wire 1 " B $end
$var wire 1 . D $end
$var wire 1 / and1 $end
$var wire 1 0 and2 $end
$var wire 1 1 bIn $end
$var wire 1 2 bOut $end
$var wire 1 3 not1 $end
$var wire 1 4 not2 $end
$var wire 1 5 xor1 $end
$upscope $end
$upscope $end
$enddefinitions $end
$comment Show the parameter values. $end
$dumpall
$end
#0
$dumpvars
x5
x4
x3
x2
x1
x0
x/
x.
x-
x,
x+
x*
x)
x(
x'
x&
x%
x$
x#
x"
x!
$end
#1
0(
14
0%
0/
0,
13
05
0*
0&
0#
0$
0+
1-
0"
0!
#3
00
x(
04
12
x%
15
1/
1*
1$
1+
1,
1"
#4
02
0/
0,
03
0-
0"
1!
#5
x2
x0
14
0%
1(
05
0*
1&
1#
0$
0+
1"
#6
0(
0)
13
0&
0#
1-
0'
0"
0!
#8
1)
1'
#9
00
04
12
15
1/
1*
1$
1+
1,
0'
1"
#10
1(
0)
1%
1'
#11
0(
02
1)
0%
0/
0,
03
0-
0'
0"
1!
#12
1(
0)
1%
1'
#13
x2
x0
14
0%
05
0*
1&
1#
0$
0+
0'
1"
#14
1)
1'
#15
0(
13
0&
0#
1-
0"
0!
#17
00
1(
04
12
0)
1%
15
1/
1*
1$
1+
1,
1"
#18
02
0/
0,
03
0-
0"
1!
#19
x2
x0
14
1)
0%
05
0*
1&
1#
0$
0+
1"
#20
02
0(
0.
00
13
0&
0#
1-
01
0"
0!
#22
12
1.
10
11
#23
1(
04
0)
1%
00
15
1/
1*
1$
1+
1,
01
1"
#24
0.
11
#25
02
1.
0/
0,
03
0-
01
0"
1!
#26
0.
11
#27
14
1)
0%
05
0*
1&
1#
0$
0+
01
1"
#28
12
1.
10
11
